<?xml version="1.0" encoding="utf-8"?>
<list>
  <item>
    <ownerid>15562</ownerid>
    <dependentid>en_thyroid_card_treatment_p</dependentid>
    <slot>nvcgSlCTHPCards</slot>
    <template>nvcgSnCTHPGuideCard</template>
  </item>
  <item>
    <ownerid>15562</ownerid>
    <dependentid>en_thyroid_research_page</dependentid>
    <slot>nvcgSlCTHPCards</slot>
    <template>nvcgSnCTHPCancerResearchCard</template>
  </item>
  <item>
    <ownerid>15562</ownerid>
    <dependentid>en_thyroid_card_causes_p</dependentid>
    <slot>nvcgSlCTHPCards</slot>
    <template>nvcgSnCTHPGuideCard</template>
  </item>
  <item>
    <ownerid>15562</ownerid>
    <dependentid>en_thyroid_card_screening_p</dependentid>
    <slot>nvcgSlCTHPCards</slot>
    <template>nvcgSnCTHPGuideCard</template>
  </item>
  <item>
    <ownerid>15562</ownerid>
    <dependentid>en_thyroid_card_survivial</dependentid>
    <slot>nvcgSlCTHPCards</slot>
    <template>nvcgSnCTHPFeatureCard</template>
  </item>
  <item>
    <ownerid>15562</ownerid>
    <dependentid>898666</dependentid>
    <slot>nvcgSlCTHPCards</slot>
    <template>nvcgSnCTHPFeatureCard</template>
  </item>
  <item>
    <ownerid>15562</ownerid>
    <dependentid>914554</dependentid>
    <slot>nvcgSlCTHPMultimedia</slot>
    <template>nvcgDsCTHPMultimedia</template>
  </item>
  <item>
    <ownerid>en_thyroid_cthp_hp</ownerid>
    <dependentid>en_thyroid_card_treatment_hp</dependentid>
    <slot>nvcgSlCTHPCards</slot>
    <template>nvcgSnCTHPGuideCard</template>
  </item>
  <item>
    <ownerid>en_thyroid_cthp_hp</ownerid>
    <dependentid>en_thyroid_research_page</dependentid>
    <slot>nvcgSlCTHPCards</slot>
    <template>nvcgSnCTHPCancerResearchCard</template>
  </item>
  <item>
    <ownerid>en_thyroid_cthp_hp</ownerid>
    <dependentid>en_thyroid_card_causes_hp</dependentid>
    <slot>nvcgSlCTHPCards</slot>
    <template>nvcgSnCTHPGuideCard</template>
  </item>
  <item>
    <ownerid>en_thyroid_cthp_hp</ownerid>
    <dependentid>en_thyroid_card_genetics_hp</dependentid>
    <slot>nvcgSlCTHPCards</slot>
    <template>nvcgSnCTHPGuideCard</template>
  </item>
  <item>
    <ownerid>en_thyroid_cthp_hp</ownerid>
    <dependentid>en_thyroid_card_screening_hp</dependentid>
    <slot>nvcgSlCTHPCards</slot>
    <template>nvcgSnCTHPGuideCard</template>
  </item>
  <item>
    <ownerid>en_thyroid_cthp_hp</ownerid>
    <dependentid>en_thyroid_card_survivial</dependentid>
    <slot>nvcgSlCTHPCards</slot>
    <template>nvcgSnCTHPFeatureCard</template>
  </item>
  <item>
    <ownerid>en_thyroid_cthp_hp</ownerid>
    <dependentid>898666</dependentid>
    <slot>nvcgSlCTHPCards</slot>
    <template>nvcgSnCTHPFeatureCard</template>
  </item>
  <item>
    <ownerid>en_thyroid_cthp_hp</ownerid>
    <dependentid>914554</dependentid>
    <slot>nvcgSlCTHPMultimedia</slot>
    <template>nvcgDsCTHPMultimedia</template>
  </item>
  <item>
    <ownerid>en_thyroid_card_treatment_p</ownerid>
    <dependentid>2898</dependentid>
    <slot>cgvRelatedPages</slot>
    <template>cgvDsRelatedResource</template>
  </item>
  <item>
    <ownerid>en_thyroid_card_treatment_p</ownerid>
    <dependentid>en_ext_link_treatment_1</dependentid>
    <slot>cgvRelatedPages</slot>
    <template>cgvDsRelatedResource</template>
  </item>
  <item>
    <ownerid>en_thyroid_card_treatment_p</ownerid>
    <dependentid>65324</dependentid>
    <slot>cgvRelatedPages</slot>
    <template>cgvDsRelatedResource</template>
  </item>
  <item>
    <ownerid>en_thyroid_card_treatment_p</ownerid>
    <dependentid>912885</dependentid>
    <slot>cgvRelatedPages</slot>
    <template>cgvDsRelatedResource</template>
  </item>
  <item>
    <ownerid>en_thyroid_card_treatment_p</ownerid>
    <dependentid>15732</dependentid>
    <slot>cgvRelatedPages</slot>
    <template>cgvDsRelatedResource</template>
  </item>
  <item>
    <ownerid>en_thyroid_card_treatment_p</ownerid>
    <dependentid>5188</dependentid>
    <slot>nvcgSlCTHPCancerSummary</slot>
    <template>nvcgSnCTHPCancerSummaryLink</template>
  </item>
  <item>
    <ownerid>en_thyroid_card_treatment_hp</ownerid>
    <dependentid>en_ext_link_treatment_1</dependentid>
    <slot>cgvRelatedPages</slot>
    <template>cgvDsRelatedResource</template>
  </item>
  <item>
    <ownerid>en_thyroid_card_treatment_hp</ownerid>
    <dependentid>65324</dependentid>
    <slot>cgvRelatedPages</slot>
    <template>cgvDsRelatedResource</template>
  </item>
  <item>
    <ownerid>en_thyroid_card_treatment_hp</ownerid>
    <dependentid>15732</dependentid>
    <slot>cgvRelatedPages</slot>
    <template>cgvDsRelatedResource</template>
  </item>
  <item>
    <ownerid>en_thyroid_card_treatment_hp</ownerid>
    <dependentid>2840</dependentid>
    <slot>cgvRelatedPages</slot>
    <template>cgvDsRelatedResource</template>
  </item>
  <item>
    <ownerid>en_thyroid_card_treatment_hp</ownerid>
    <dependentid>14298</dependentid>
    <slot>cgvRelatedPages</slot>
    <template>cgvDsRelatedResource</template>
  </item>
  <item>
    <ownerid>en_thyroid_card_treatment_hp</ownerid>
    <dependentid>3504</dependentid>
    <slot>nvcgSlCTHPCancerSummary</slot>
    <template>nvcgSnCTHPCancerSummaryLink</template>
  </item>
  <item>
    <ownerid>en_thyroid_card_causes_p</ownerid>
    <dependentid>6158</dependentid>
    <slot>cgvRelatedPages</slot>
    <template>cgvDsRelatedResource</template>
  </item>
  <item>
    <ownerid>en_thyroid_card_causes_p</ownerid>
    <dependentid>860833</dependentid>
    <slot>cgvRelatedPages</slot>
    <template>cgvDsRelatedResource</template>
  </item>
  <item>
    <ownerid>en_thyroid_card_causes_hp</ownerid>
    <dependentid>1654</dependentid>
    <slot>cgvRelatedPages</slot>
    <template>cgvDsRelatedResource</template>
  </item>
  <item>
    <ownerid>en_thyroid_card_screening_p</ownerid>
    <dependentid>6145</dependentid>
    <slot>cgvRelatedPages</slot>
    <template>cgvDsRelatedResource</template>
  </item>
  <item>
    <ownerid>en_thyroid_card_screening_hp</ownerid>
    <dependentid>1541</dependentid>
    <slot>cgvRelatedPages</slot>
    <template>cgvDsRelatedResource</template>
  </item>
  <item>
    <ownerid>en_thyroid_card_survivial</ownerid>
    <dependentid>en_ext_link_survival</dependentid>
    <slot>nvcgSlCTHPFeaturedItem</slot>
    <template>nvcgSnCTHPFeaturedItem</template>
  </item>
  <item>
    <ownerid>en_ext_link_survival</ownerid>
    <dependentid>919687</dependentid>
    <slot>gloImageSl</slot>
    <template>gloSnImage</template>
  </item>
  <item>
    <ownerid>en_thyroid_card_genetics_hp</ownerid>
    <dependentid>3040</dependentid>
    <slot>nvcgSlCTHPCancerSummary</slot>
    <template>nvcgSnCTHPCancerSummaryLink</template>
  </item>
  <item>
    <ownerid>en_thyroid_card_genetics_hp</ownerid>
    <dependentid>2569</dependentid>
    <slot>nvcgSlCTHPCancerSummary</slot>
    <template>nvcgSnCTHPCancerSummaryLink</template>
  </item>
  <item>
    <ownerid>en_section_nav</ownerid>
    <dependentid>/cancertopics/types/thyroid</dependentid>
    <slot>nciSectionNavRootNavOn </slot>
    <template>nciSnSectionNavRoot</template>
  </item>
  <item>
    <ownerid>/cancertopics/types/thyroid</ownerid>
    <dependentid>en_section_nav</dependentid>
    <slot>nvcgSlSectionNav</slot>
    <template>nvcgSnSectionNav</template>
  </item>
  <item>
    <ownerid>/cancertopics/types/thyroid/hp</ownerid>
    <dependentid>en_thyroid_cthp_hp</dependentid>
    <slot>rffNavLandingPage</slot>
    <template>cgvSnTitleLink</template>
  </item>
  <item>
    <ownerid>/cancertopics/types/thyroid/research</ownerid>
    <dependentid>en_thyroid_research_page</dependentid>
    <slot>rffNavLandingPage</slot>
    <template>cgvSnTitleLink</template>
  </item>
  <item>
    <ownerid>/cancertopics/types/thyroid/patient</ownerid>
    <dependentid>15562</dependentid>
    <slot>rffNavLandingPage</slot>
    <template>cgvSnTitleLink</template>
  </item>
  <item>
    <ownerid>15562</ownerid>
    <dependentid>en_thyroid_cthp_hp</dependentid>
    <slot>nvcgSlCTHPAudienceToggle</slot>
    <template>nvcgSnCTHPAudienceToggle</template>
  </item>
  <item>
    <ownerid>en_thyroid_cthp_hp</ownerid>
    <dependentid>15562</dependentid>
    <slot>nvcgSlCTHPAudienceToggle</slot>
    <template>nvcgSnCTHPAudienceToggle</template>
  </item>
  <item>
    <ownerid>153789</ownerid>
    <dependentid>es_thyroid_card_treatment_p</dependentid>
    <slot>nvcgSlCTHPCards</slot>
    <template>nvcgSnCTHPGuideCard</template>
  </item>
  <item>
    <ownerid>153789</ownerid>
    <dependentid>es_thyroid_research_page</dependentid>
    <slot>nvcgSlCTHPCards</slot>
    <template>nvcgSnCTHPCancerResearchCard</template>
  </item>
  <item>
    <ownerid>153789</ownerid>
    <dependentid>es_thyroid_card_causes_p</dependentid>
    <slot>nvcgSlCTHPCards</slot>
    <template>nvcgSnCTHPGuideCard</template>
  </item>
  <item>
    <ownerid>153789</ownerid>
    <dependentid>es_thyroid_card_screening_p</dependentid>
    <slot>nvcgSlCTHPCards</slot>
    <template>nvcgSnCTHPGuideCard</template>
  </item>
  <item>
    <ownerid>153789</ownerid>
    <dependentid>es_thyroid_card_survivial</dependentid>
    <slot>nvcgSlCTHPCards</slot>
    <template>nvcgSnCTHPFeatureCard</template>
  </item>
  <item>
    <ownerid>153789</ownerid>
    <dependentid>918819</dependentid>
    <slot>nvcgSlCTHPCards</slot>
    <template>nvcgSnCTHPFeatureCard</template>
  </item>
  <item>
    <ownerid>153789</ownerid>
    <dependentid>918842</dependentid>
    <slot>nvcgSlCTHPMultimedia</slot>
    <template>nvcgDsCTHPMultimedia</template>
  </item>
  <item>
    <ownerid>es_thyroid_cthp_hp</ownerid>
    <dependentid>es_thyroid_card_treatment_hp</dependentid>
    <slot>nvcgSlCTHPCards</slot>
    <template>nvcgSnCTHPGuideCard</template>
  </item>
  <item>
    <ownerid>es_thyroid_cthp_hp</ownerid>
    <dependentid>es_thyroid_research_page</dependentid>
    <slot>nvcgSlCTHPCards</slot>
    <template>nvcgSnCTHPCancerResearchCard</template>
  </item>
  <item>
    <ownerid>es_thyroid_cthp_hp</ownerid>
    <dependentid>es_thyroid_card_causes_hp</dependentid>
    <slot>nvcgSlCTHPCards</slot>
    <template>nvcgSnCTHPGuideCard</template>
  </item>
  <item>
    <ownerid>es_thyroid_cthp_hp</ownerid>
    <dependentid>es_thyroid_card_screening_hp</dependentid>
    <slot>nvcgSlCTHPCards</slot>
    <template>nvcgSnCTHPGuideCard</template>
  </item>
  <item>
    <ownerid>es_thyroid_cthp_hp</ownerid>
    <dependentid>es_thyroid_card_survivial</dependentid>
    <slot>nvcgSlCTHPCards</slot>
    <template>nvcgSnCTHPFeatureCard</template>
  </item>
  <item>
    <ownerid>es_thyroid_cthp_hp</ownerid>
    <dependentid>918819</dependentid>
    <slot>nvcgSlCTHPCards</slot>
    <template>nvcgSnCTHPFeatureCard</template>
  </item>
  <item>
    <ownerid>es_thyroid_cthp_hp</ownerid>
    <dependentid>918842</dependentid>
    <slot>nvcgSlCTHPMultimedia</slot>
    <template>nvcgDsCTHPMultimedia</template>
  </item>
  <item>
    <ownerid>es_thyroid_card_treatment_p</ownerid>
    <dependentid>9935</dependentid>
    <slot>cgvRelatedPages</slot>
    <template>cgvDsRelatedResource</template>
  </item>
  <item>
    <ownerid>es_thyroid_card_treatment_p</ownerid>
    <dependentid>es_ext_link_treatment_1</dependentid>
    <slot>cgvRelatedPages</slot>
    <template>cgvDsRelatedResource</template>
  </item>
  <item>
    <ownerid>es_thyroid_card_treatment_p</ownerid>
    <dependentid>917514</dependentid>
    <slot>cgvRelatedPages</slot>
    <template>cgvDsRelatedResource</template>
  </item>
  <item>
    <ownerid>es_thyroid_card_treatment_p</ownerid>
    <dependentid>15505</dependentid>
    <slot>cgvRelatedPages</slot>
    <template>cgvDsRelatedResource</template>
  </item>
  <item>
    <ownerid>es_thyroid_card_treatment_p</ownerid>
    <dependentid>10624</dependentid>
    <slot>nvcgSlCTHPCancerSummary</slot>
    <template>nvcgSnCTHPCancerSummaryLink</template>
  </item>
  <item>
    <ownerid>es_thyroid_card_treatment_hp</ownerid>
    <dependentid>es_ext_link_treatment_1</dependentid>
    <slot>cgvRelatedPages</slot>
    <template>cgvDsRelatedResource</template>
  </item>
  <item>
    <ownerid>es_thyroid_card_treatment_hp</ownerid>
    <dependentid>15505</dependentid>
    <slot>cgvRelatedPages</slot>
    <template>cgvDsRelatedResource</template>
  </item>
  <item>
    <ownerid>es_thyroid_card_treatment_hp</ownerid>
    <dependentid>9022</dependentid>
    <slot>cgvRelatedPages</slot>
    <template>cgvDsRelatedResource</template>
  </item>
  <item>
    <ownerid>es_thyroid_card_treatment_hp</ownerid>
    <dependentid>15539</dependentid>
    <slot>cgvRelatedPages</slot>
    <template>cgvDsRelatedResource</template>
  </item>
  <item>
    <ownerid>es_thyroid_card_treatment_hp</ownerid>
    <dependentid>8397</dependentid>
    <slot>nvcgSlCTHPCancerSummary</slot>
    <template>nvcgSnCTHPCancerSummaryLink</template>
  </item>
  <item>
    <ownerid>es_thyroid_card_causes_p</ownerid>
    <dependentid>411288</dependentid>
    <slot>cgvRelatedPages</slot>
    <template>cgvDsRelatedResource</template>
  </item>
  <item>
    <ownerid>es_thyroid_card_causes_hp</ownerid>
    <dependentid>411309</dependentid>
    <slot>cgvRelatedPages</slot>
    <template>cgvDsRelatedResource</template>
  </item>
  <item>
    <ownerid>es_thyroid_card_screening_p</ownerid>
    <dependentid>411225</dependentid>
    <slot>cgvRelatedPages</slot>
    <template>cgvDsRelatedResource</template>
  </item>
  <item>
    <ownerid>es_thyroid_card_screening_hp</ownerid>
    <dependentid>411248</dependentid>
    <slot>cgvRelatedPages</slot>
    <template>cgvDsRelatedResource</template>
  </item>
  <item>
    <ownerid>es_thyroid_card_survivial</ownerid>
    <dependentid>es_ext_link_survival</dependentid>
    <slot>nvcgSlCTHPFeaturedItem</slot>
    <template>nvcgSnCTHPFeaturedItem</template>
  </item>
  <item>
    <ownerid>es_ext_link_survival</ownerid>
    <dependentid>919687</dependentid>
    <slot>gloImageSl</slot>
    <template>gloSnImage</template>
  </item>
  <item>
    <ownerid>es_section_nav</ownerid>
    <dependentid>/espanol/tipos/tiroides</dependentid>
    <slot>nciSectionNavRootNavOn </slot>
    <template>nciSnSectionNavRoot</template>
  </item>
  <item>
    <ownerid>/espanol/tipos/tiroides</ownerid>
    <dependentid>es_section_nav</dependentid>
    <slot>nvcgSlSectionNav</slot>
    <template>nvcgSnSectionNav</template>
  </item>
  <item>
    <ownerid>/espanol/tipos/tiroides/pro</ownerid>
    <dependentid>es_thyroid_cthp_hp</dependentid>
    <slot>rffNavLandingPage</slot>
    <template>cgvSnTitleLink</template>
  </item>
  <item>
    <ownerid>/espanol/tipos/tiroides/investigacion</ownerid>
    <dependentid>es_thyroid_research_page</dependentid>
    <slot>rffNavLandingPage</slot>
    <template>cgvSnTitleLink</template>
  </item>
  <item>
    <ownerid>/espanol/tipos/tiroides/paciente</ownerid>
    <dependentid>153789</dependentid>
    <slot>rffNavLandingPage</slot>
    <template>cgvSnTitleLink</template>
  </item>
  <item>
    <ownerid>153789</ownerid>
    <dependentid>es_thyroid_cthp_hp</dependentid>
    <slot>nvcgSlCTHPAudienceToggle</slot>
    <template>nvcgSnCTHPAudienceToggle</template>
  </item>
  <item>
    <ownerid>es_thyroid_cthp_hp</ownerid>
    <dependentid>153789</dependentid>
    <slot>nvcgSlCTHPAudienceToggle</slot>
    <template>nvcgSnCTHPAudienceToggle</template>
  </item>
  <item>
    <ownerid>en_thyroid_research_page</ownerid>
    <dependentid>488738</dependentid>
    <slot>nvcgSlCancerResearchLinks</slot>
    <template>gloSnListItem</template>
  </item>
  <item>
    <ownerid>en_thyroid_research_page</ownerid>
    <dependentid>912173</dependentid>
    <slot>nvcgSlCancerResearchLinks</slot>
    <template>gloSnListItem</template>
  </item>
  <item>
    <ownerid>en_thyroid_research_page</ownerid>
    <dependentid>842607</dependentid>
    <slot>nvcgSlCancerResearchLinks</slot>
    <template>gloSnListItem</template>
  </item>
  <item>
    <ownerid>en_thyroid_research_page</ownerid>
    <dependentid>772122</dependentid>
    <slot>nvcgSlCancerResearchLinks</slot>
    <template>gloSnListItem</template>
  </item>
  <item>
    <ownerid>en_thyroid_research_page</ownerid>
    <dependentid>315480</dependentid>
    <slot>nvcgSlCancerResearchLinks</slot>
    <template>gloSnListItem</template>
  </item>
  <item>
    <ownerid>en_thyroid_research_page</ownerid>
    <dependentid>225392</dependentid>
    <slot>nvcgSlCancerResearchLinks</slot>
    <template>gloSnListItem</template>
  </item>
  <item>
    <ownerid>en_thyroid_research_page</ownerid>
    <dependentid>139034</dependentid>
    <slot>nvcgSlCancerResearchLinks</slot>
    <template>gloSnListItem</template>
  </item>
  <item>
    <ownerid>es_thyroid_research_page</ownerid>
    <dependentid>725793</dependentid>
    <slot>nvcgSlCancerResearchLinks</slot>
    <template>gloSnListItem</template>
  </item>
</list>