<?xml version="1.0" encoding="utf-8"?>
<list>
  <item>
    <mig_id>13658</mig_id>
    <community>site</community>
    <contenttype>cgvCancerTypeHome</contenttype>
    <folder>/cancertopics/types/small-intestine</folder>
    <sys_lang><![CDATA[en-us]]></sys_lang>
    <long_title><![CDATA[Small Intestine Cancer]]></long_title>
    <short_title><![CDATA[Small Intestine Cancer]]></short_title>
    <long_description><![CDATA[NCI's gateway for information about Small Intestine Cancer.]]></long_description>
    <bodyfield><![CDATA[<p>The small intestine (also called small bowel) is part of the body’s digestive system. It is a long, coiled tube that connects the stomach to the large intestine. The small intestine receives food from the stomach, helps break it down, and absorbs nutrients that are used by the body. The three parts of the small intestine are the duodenum, jejunum, and ileum. The duodenum connects to the stomach, and the ileum connects to the colon.</p>
<p>Small intestine cancer often starts in the duodenum. The most common type of small intestine cancer is adenocarcinoma (cancer that begins in cells that make and release mucus and other fluids). Other types of small intestine cancer are sarcomas, carcinoid tumors, gastrointestinal stromal tumors, and lymphomas.</p>]]></bodyfield>
    <audience><![CDATA[patient]]></audience>
  </item>
  <item>
    <mig_id>/cancertopics/types/small-intestine</mig_id>
    <community>site</community>
    <contenttype>rffNavon</contenttype>
    <folder>/cancertopics/types/small-intestine</folder>
    <sys_lang><![CDATA[en-us]]></sys_lang>
    <nav_title><![CDATA[Small Intestine Cancer]]></nav_title>
  </item>
  <item>
    <mig_id>/cancertopics/types/small-intestine/patient</mig_id>
    <community>site</community>
    <contenttype>rffNavon</contenttype>
    <folder>/cancertopics/types/small-intestine/patient</folder>
    <sys_lang><![CDATA[en-us]]></sys_lang>
    <nav_title><![CDATA[Patient]]></nav_title>
  </item>
  <item>
    <mig_id>/cancertopics/types/small-intestine/hp</mig_id>
    <community>site</community>
    <contenttype>rffNavon</contenttype>
    <folder>/cancertopics/types/small-intestine/hp</folder>
    <sys_lang><![CDATA[en-us]]></sys_lang>
    <nav_title><![CDATA[Health Professional]]></nav_title>
  </item>
  <item>
    <mig_id>320761</mig_id>
    <community>site</community>
    <contenttype>cgvCancerTypeHome</contenttype>
    <folder>/espanol/tipos/intestino-delgado</folder>
    <sys_lang><![CDATA[es-us]]></sys_lang>
    <long_title><![CDATA[Cáncer de intestino delgado]]></long_title>
    <short_title><![CDATA[Cáncer de intestino delgado]]></short_title>
    <long_description><![CDATA[Cáncer de intestino delgado]]></long_description>
    <bodyfield><![CDATA[<p>El intestino delgado forma parte del aparato digestivo del cuerpo. Es un tubo largo con forma de espiral que conecta el estómago con el intestino grueso. El intestino delgado recibe alimentos del estómago, ayuda a descomponerlos y absorbe los nutrientes que utiliza el cuerpo. Las tres partes del intestino delgado son el duodeno, el yeyuno y el íleon. El duodeno se conecta con el estómago y el íleon se conecta con el colon.</p>
<p>El cáncer de intestino delgado a menudo comienza en el duodeno. El tipo más común de cáncer de intestino delgado es el adenocarcinoma (cáncer que empieza en las células que producen y liberan moco y otros líquidos). Otros tipos de cáncer de intestino delgado son sarcomas, tumores carcinoides, tumores del estroma gastrointestinal y linfomas.</p>]]></bodyfield>
    <audience><![CDATA[patient]]></audience>
  </item>
  <item>
    <mig_id>/espanol/tipos/intestino-delgado</mig_id>
    <community>site</community>
    <contenttype>rffNavon</contenttype>
    <folder>/espanol/tipos/intestino-delgado</folder>
    <sys_lang><![CDATA[es-us]]></sys_lang>
    <nav_title><![CDATA[Cáncer de intestino delgado]]></nav_title>
  </item>
  <item>
    <mig_id>/espanol/tipos/intestino-delgado/paciente</mig_id>
    <community>site</community>
    <contenttype>rffNavon</contenttype>
    <folder>/espanol/tipos/intestino-delgado/paciente</folder>
    <sys_lang><![CDATA[es-us]]></sys_lang>
    <nav_title><![CDATA[Paciente]]></nav_title>
  </item>
  <item>
    <mig_id>/espanol/tipos/intestino-delgado/pro</mig_id>
    <community>site</community>
    <contenttype>rffNavon</contenttype>
    <folder>/espanol/tipos/intestino-delgado/pro</folder>
    <sys_lang><![CDATA[es-us]]></sys_lang>
    <nav_title><![CDATA[Profesionales de salud]]></nav_title>
  </item>
</list>